setup.cfg
setup.py
Yellowfin.egg-info/PKG-INFO
Yellowfin.egg-info/SOURCES.txt
Yellowfin.egg-info/dependency_links.txt
Yellowfin.egg-info/requires.txt
Yellowfin.egg-info/top_level.txt
yellowfin/__init__.py