Metadata-Version: 1.1
Name: Yellowfin
Version: 1.0.2
Summary: A Python module to handle Yellowfin BI Tool
Home-page: https://github.com/Onsight-Solutions/Python-Yellowfin
Author: Onsight Solutions
Author-email: mss@onsight.nl
License: GPLv2
Keywords: yellowfin BI API
Platform: UNKNOWN
Classifier: Development Status :: 4 - Beta
Classifier: Intended Audience :: Developers
Classifier: License :: OSI Approved :: GNU General Public License v2 (GPLv2)
Classifier: Natural Language :: English
Classifier: Programming Language :: Python :: 2.7
